Metadata-Version: 2.1
Name: tailscale-util-ns
Version: 2.0.1
Summary: TailScale util to get device details
Home-page: https://github.com/nishithcitc/tailscale-util-ns
Author: Nishith Shah
Author-email: nshthshah@gmail.com
License: UNKNOWN
Platform: UNKNOWN
License-File: LICENSE
